auth/__init__.py
auth/abstract_datastore.py
auth/credentials.py
auth/credentials_helpers.py
auth/credentials_helpers_test.py
auth/credentials_test.py
auth/decorators.py
auth/decorators_test.py
auth/exceptions.py
auth/cli/key_upload.py
auth/cli/key_upload_test.py
auth/datastore/__init__.py
auth/datastore/cloud_storage.py
auth/datastore/cloud_storage_test.py
auth/datastore/file_datastore.py
auth/datastore/firestore.py
auth/datastore/local_file.py
auth/datastore/local_file_test.py
auth/datastore/secret_manager.py
python_oauth_token_manager-1.0.2.dist-info/LICENSE
python_oauth_token_manager-1.0.2.dist-info/METADATA
python_oauth_token_manager-1.0.2.dist-info/WHEEL
python_oauth_token_manager-1.0.2.dist-info/top_level.txt
python_oauth_token_manager-1.0.2.dist-info/RECORD
