Metadata-Version: 2.2
Name: python-oauth-token-manager
Version: 1.0.2
Summary: API for managing stored OAuth credentials.
Author-email: David Harcombe <david.harcombe@gmail.com>
License: Apache 2.0
Project-URL: Homepage, https://github.com/googleworkspace/python-oauth-token-manager
Project-URL: Bug Tracker, https://github.com/googleworkspace/python-oauth-token-manager/issues
Classifier: Programming Language :: Python :: 3
Classifier: Operating System :: OS Independent
Requires-Python: >=3.10
License-File: LICENSE
Requires-Dist: dataclasses-json>=0.5.2
Requires-Dist: decorator>=4.4.2
Requires-Dist: gcs-oauth2-boto-plugin>=2.7
Requires-Dist: gcsfs>=0.7.2
Requires-Dist: google-api-core>=1.26.1
Requires-Dist: google-api-python-client>=2.0.2
Requires-Dist: google-auth-httplib2>=0.1.0
Requires-Dist: google-auth-oauthlib>=0.4.3
Requires-Dist: google-auth>=1.28.0
Requires-Dist: google-cloud-core>=1.6.0
Requires-Dist: google-cloud-firestore>=2.0.2
Requires-Dist: google-cloud-secret-manager>=2.8.0
Requires-Dist: google-cloud-storage>=1.36.2
Requires-Dist: google-reauth>=0.1.1
Requires-Dist: googleapis-common-protos>=1.53.0
Requires-Dist: httplib2>=0.19.0
Requires-Dist: oauth2client>=4.1.3
Requires-Dist: oauthlib>=3.1.0
Requires-Dist: pytz>=2021.1
Requires-Dist: requests-oauthlib>=1.3.0
Requires-Dist: requests>=2.27.1
